MANIFEST.in
README.md
requirements.txt
setup.cfg
setup.py
iou/ReferenceModel.py
iou/__init__.py
iou/run.py
iou/version.py
iou/data/__init__.py
iou/data/__init__.pyc
iou/data/transactions.csv
iou/data/__pycache__/__init__.cpython-36.pyc
py_iou.egg-info/PKG-INFO
py_iou.egg-info/SOURCES.txt
py_iou.egg-info/dependency_links.txt
py_iou.egg-info/entry_points.txt
py_iou.egg-info/requires.txt
py_iou.egg-info/top_level.txt