Metadata-Version: 1.0
Name: py-iou
Version: 1.1.1
Summary: A python package to find optimal number of transactions betweeen friends
Home-page: https://github.com/kdheepak/iou
Author: Dheepak Krishnamurthy
Author-email: kdheepak89@gmail.com
License: Revised BSD License
Platform: UNKNOWN
